ModelForge/__init__.py
ModelForge/app.py
ModelForge/app_old.py
ModelForge/cli.py
ModelForge/cli_old.py
ModelForge/dependencies.py
ModelForge/exceptions.py
ModelForge/logging_config.py
ModelForge/Frontend/build/asset-manifest.json
ModelForge/Frontend/build/manifest.json
ModelForge/database/__init__.py
ModelForge/database/database_manager.py
ModelForge/database/models.py
ModelForge/evaluation/__init__.py
ModelForge/evaluation/dataset_validator.py
ModelForge/evaluation/metrics.py
ModelForge/formatters/__init__.py
ModelForge/formatters/formatting_functions.py
ModelForge/globals/__init__.py
ModelForge/globals/globals.py
ModelForge/globals/globals_instance.py
ModelForge/model_configs/high_end.json
ModelForge/model_configs/low_end.json
ModelForge/model_configs/mid_range.json
ModelForge/providers/__init__.py
ModelForge/providers/huggingface_provider.py
ModelForge/providers/provider_factory.py
ModelForge/providers/unsloth_provider.py
ModelForge/routers/__init__.py
ModelForge/routers/finetuning_router.py
ModelForge/routers/finetuning_router_old.py
ModelForge/routers/hub_management_router.py
ModelForge/routers/models_router.py
ModelForge/routers/models_router_old.py
ModelForge/routers/playground_router.py
ModelForge/schemas/__init__.py
ModelForge/schemas/training_schemas.py
ModelForge/services/__init__.py
ModelForge/services/hardware_service.py
ModelForge/services/model_service.py
ModelForge/services/training_service.py
ModelForge/strategies/__init__.py
ModelForge/strategies/dpo_strategy.py
ModelForge/strategies/qlora_strategy.py
ModelForge/strategies/rlhf_strategy.py
ModelForge/strategies/sft_strategy.py
ModelForge/strategies/strategy_factory.py
ModelForge/test_datasets/low_qa_train_set.jsonl
ModelForge/test_datasets/low_summarization_train_set.jsonl
ModelForge/test_datasets/low_text_generation.jsonl
ModelForge/test_datasets/med_construction.jsonl
ModelForge/test_datasets/med_text_generation.jsonl
ModelForge/test_datasets/question_answer-train-data-sample.jsonl
modelforge_finetuning-2.0.5.dist-info/licenses/LICENSE
modelforge_finetuning-2.0.5.dist-info/METADATA
modelforge_finetuning-2.0.5.dist-info/WHEEL
modelforge_finetuning-2.0.5.dist-info/entry_points.txt
modelforge_finetuning-2.0.5.dist-info/top_level.txt
modelforge_finetuning-2.0.5.dist-info/RECORD
