Metadata-Version: 2.4
Name: modelforge-finetuning
Version: 2.0.5
Summary: ModelForge: A no-code toolkit for fine-tuning HuggingFace models
Author-email: R3tr0 M1ll3r <r3tr0.m1ll3r@gmail.com>
Project-URL: Documentation, https://modelforge-finetuning.readthedocs.io
Requires-Python: <3.12,>=3.11
License-File: LICENSE
Requires-Dist: accelerate==1.5.2
Requires-Dist: bitsandbytes==0.45.3
Requires-Dist: datasets==3.5.0
Requires-Dist: dotenv>=0.9.9
Requires-Dist: fastapi==0.115.12
Requires-Dist: huggingface-hub==0.30.2
Requires-Dist: safetensors==0.5.3
Requires-Dist: setuptools==78.1.0
Requires-Dist: tensorboard==2.19.0
Requires-Dist: tensorboard-data-server==0.7.2
Requires-Dist: tokenizers==0.21.0
Requires-Dist: tqdm==4.67.1
Requires-Dist: transformers==4.48.3
Requires-Dist: trl==0.16.0
Requires-Dist: uvicorn
Requires-Dist: platformdirs
Requires-Dist: pynvml
Requires-Dist: peft
Requires-Dist: python-multipart
Requires-Dist: sqlalchemy>=2.0.44
Dynamic: license-file
